FontColors/__init__.py
FontColors/back.py
FontColors/color.py
FontColors/style.py
ChromaStyler-1.1.0.dist-info/LICENCE
ChromaStyler-1.1.0.dist-info/METADATA
ChromaStyler-1.1.0.dist-info/WHEEL
ChromaStyler-1.1.0.dist-info/top_level.txt
ChromaStyler-1.1.0.dist-info/RECORD
