Metadata-Version: 2.1
Name: ChromaStyler
Version: 1.1.0
Summary: none
Author: Arsam
Author-email: ashouriarsam@gmail.com
License-File: LICENCE
